AUTHORS.rst
CHANGELOG.rst
HACKING.rst
LICENSE
MANIFEST.in
README.rst
setup.py
theblues/__init__.py
theblues/charmstore.py
theblues/errors.py
theblues/identity_manager.py
theblues/jimm.py
theblues/plans.py
theblues/support.py
theblues/terms.py
theblues/utils.py
theblues.egg-info/PKG-INFO
theblues.egg-info/SOURCES.txt
theblues.egg-info/dependency_links.txt
theblues.egg-info/not-zip-safe
theblues.egg-info/requires.txt
theblues.egg-info/top_level.txt