Metadata-Version: 1.1
Name: theblues
Version: 0.5.0
Summary: Python library for using the juju charm store API.
Home-page: https://github.com/juju/theblues
Author: Juju GUI Developers
Author-email: juju-gui@lists.ubuntu.com
License: UNKNOWN
Keywords: theblues
Platform: UNKNOWN
Classifier: Development Status :: 3 - Alpha
Classifier: Intended Audience :: Developers
Classifier: License :: OSI Approved :: GNU Lesser General Public License v3 (LGPLv3)
Classifier: Natural Language :: English
Classifier: Programming Language :: Python :: 2
Classifier: Programming Language :: Python :: 2.7
Classifier: Programming Language :: Python :: 3
Classifier: Programming Language :: Python :: 3.4
